pirtpal_singh_remove_outliers/outliers.py
pritpal_singh_remove_outliers/outliers.py
Outlier_removal_101883058-1.0.3.dist-info/LICENSE.txt
Outlier_removal_101883058-1.0.3.dist-info/METADATA
Outlier_removal_101883058-1.0.3.dist-info/WHEEL
Outlier_removal_101883058-1.0.3.dist-info/entry_points.txt
Outlier_removal_101883058-1.0.3.dist-info/top_level.txt
Outlier_removal_101883058-1.0.3.dist-info/RECORD
