Metadata-Version: 2.1
Name: Outlier-removal-101883058
Version: 1.0.3
Summary: Removing outliers using IQR(Interquartile) range(25%-75%).
Home-page: UNKNOWN
Author: Pritpal Singh Pruthi
Author-email: psp.ps001@gmail.com
License: MIT
Platform: UNKNOWN
Classifier: License :: OSI Approved :: MIT License
Classifier: Programming Language :: Python :: 3
Classifier: Programming Language :: Python :: 3.4
Classifier: Programming Language :: Python :: 3.5
Classifier: Programming Language :: Python :: 3.6
Classifier: Programming Language :: Python :: 3.7
Requires-Dist: numpy
Requires-Dist: pandas
